Workbook

Sheet statements
B1: Financial Statements
A3: X | B3: Income Statement
B4: Figures in USD millions | D4: =D17 -> 2026 | E4: =E17 -> 2027 | F4: =F17 -> 2028 | G4: =G17 -> 2029 | H4: =H17 -> 2030
B5: Revenue | D5: =D63*D64 -> 198380 | E5: =E63*E64 -> 208299 | F5: =F63*F64 -> 223177.5 | G5: =G63*G64 -> 235576.25 | H5: =H63*H64 -> 247975
B6: COGS | D6: =-D66*D5 -> -85303.4 | E6: =-E66*E5 -> -89568.57 | F6: =-F66*F5 -> -89271 | G6: =-G66*G5 -> -89518.975 | H6: =-H66*H5 -> -94230.5
B7: Gross Profit | D7: =D5+D6 -> 113076.6 | E7: =E5+E6 -> 118730.43 | F7: =F5+F6 -> 133906.5 | G7: =G5+G6 -> 146057.27 | H7: =H5+H6 -> 153744.5
B8: SG&A | D8: =-D67*D5 -> -69433 | E8: =-E67*E5 -> -72904.65 | F8: =-F67*F5 -> -78112.125 | G8: =-G67*G5 -> -82451.688 | H8: =-H67*H5 -> -86791.25
B9: Depreciation | D9: =-D100 -> -6399 | E9: =-E100 -> -7599 | F9: =-F100 -> -8599 | G9: =-G100 -> -9349 | H9: =-H100 -> -10099
B10: Operating Profit | D10: =D7+D8+D9 -> 37244.6 | E10: =E7+E8+E9 -> 38226.78 | F10: =F7+F8+F9 -> 47195.375 | G10: =G7+G8+G9 -> 54256.587 | H10: =H7+H8+H9 -> 56854.25
B11: Interest | D11: =D130 -> 2800 | E11: =E130 -> 2800 | F11: =F130 -> 2800 | G11: =G130 -> 2800 | H11: =H130 -> 2800
B12: Earnings Before Tax | D12: =D10-D11 -> 34444.6 | E12: =E10-E11 -> 35426.78 | F12: =F10-F11 -> 44395.375 | G12: =G10-G11 -> 51456.587 | H12: =H10-H11 -> 54054.25
B13: Taxes | D13: =D69*D12 -> 7233.366 | E13: =E69*E12 -> 7439.6238 | F13: =F69*F12 -> 9323.0287 | G13: =G69*G12 -> 10805.883 | H13: =H69*H12 -> 11351.392
B14: Net Income | D14: =D12-D13 -> 27211.234 | E14: =E12-E13 -> 27987.156 | F14: =F12-F13 -> 35072.346 | G14: =G12-G13 -> 40650.704 | H14: =H12-H13 -> 42702.857
A16: X | B16: Balance Sheet
B17: Figures in USD | C17: 2025 | D17: =C17+1 -> 2026 | E17: =D17+1 -> 2027 | F17: =E17+1 -> 2028 | G17: =F17+1 -> 2029 | H17: =G17+1 -> 2030
B18: Cash & Cash Equivalents | C18: 14589 | D18: =D59 -> 21534.405 | E18: =E59 -> 32358.52 | F18: =F59 -> 50080.897 | G18: =G59 -> 71830.972 | H18: =H59 -> 91753.805 | I18: CFS
B19: Accounts Receivable | C19: 9877 | D19: =D5*D75 -> 12323.498 | E19: =E5*E75 -> 12939.673 | F19: =F5*F75 -> 13863.936 | G19: =G5*G75 -> 14634.154 | H19: =H5*H75 -> 15404.373
B20: Inventory | C20: 8579 | D20: =-D6*D76 -> 9643.2667 | E20: =-E6*E76 -> 10125.43 | F20: =-F6*F76 -> 10091.791 | G20: =-G6*G76 -> 10119.824 | H20: =-H6*H76 -> 10652.446
B21: Total Current Assets | C21: =SUM(C18:C20) -> 33045 | D21: =SUM(D18:D20) -> 43501.17 | E21: =SUM(E18:E20) -> 55423.623 | F21: =SUM(F18:F20) -> 74036.623 | G21: =SUM(G18:G20) -> 96584.949 | H21: =SUM(H18:H20) -> 117810.62
B22: Property Plant & Equipment (PPE) | C22: 48990 | D22: =D105 -> 57591 | E22: =E105 -> 61992 | F22: =F105 -> 63393 | G22: =G105 -> 61544 | H22: =H105 -> 58945 | I22: FA Schedule
B23: Total Assets | C23: =SUM(C21,C22) -> 82035 | D23: =SUM(D21,D22) -> 101092.17 | E23: =SUM(E21,E22) -> 117415.62 | F23: =SUM(F21,F22) -> 137429.62 | G23: =SUM(G21,G22) -> 158128.95 | H23: =SUM(H21,H22) -> 176755.62
B25: Accounts Payable | C25: 14880 | D25: =-D6*D77 -> 16725.936 | E25: =-E6*E77 -> 17562.233 | F25: =-F6*F77 -> 17503.887 | G25: =-G6*G77 -> 17552.509 | H25: =-H6*H77 -> 18476.325
B26: Revolver | C26: 0 | D26: =D126 -> 0 | E26: =E126 -> 0 | F26: =F126 -> 0 | G26: =G126 -> 0 | H26: =H126 -> 0 | I26: Revolver Schedule
B27: Total Current Liabilities | C27: =SUM(C25,C26) -> 14880 | D27: =SUM(D25,D26) -> 16725.936 | E27: =SUM(E25,E26) -> 17562.233 | F27: =SUM(F25,F26) -> 17503.887 | G27: =SUM(G25,G26) -> 17552.509 | H27: =SUM(H25,H26) -> 18476.325
B29: Long Term Debt | C29: 40000 | D29: =D79 -> 40000 | E29: =E79 -> 40000 | F29: =F79 -> 40000 | G29: =G79 -> 40000 | H29: =H79 -> 40000
B30: Total Liabilities | C30: =SUM(C27,C29) -> 54880 | D30: =SUM(D27,D29) -> 56725.936 | E30: =SUM(E27,E29) -> 57562.233 | F30: =SUM(F27,F29) -> 57503.887 | G30: =SUM(G27,G29) -> 57552.509 | H30: =SUM(H27,H29) -> 58476.325
B32: Common stock | C32: 25000 | D32: 25000 | E32: 25000 | F32: 25000 | G32: 25000 | H32: 25000 | I32: Share capital = No. of equity shares * Face Value per share
B33: Retained Earnings | C33: =24155-22000 -> 2155 | D33: =D111 -> 19366.234 | E33: =E111 -> 34853.39 | F33: =F111 -> 54925.736 | G33: =G111 -> 75576.441 | H33: =H111 -> 93279.298 | I33: RE Schedule
B34: Total Shareholders' Equity | C34: =SUM(C32:C33) -> 27155 | D34: =SUM(D32:D33) -> 44366.234 | E34: =SUM(E32:E33) -> 59853.39 | F34: =SUM(F32:F33) -> 79925.736 | G34: =SUM(G32:G33) -> 100576.44 | H34: =SUM(H32:H33) -> 118279.3
B36: Total Liabilities & Equity | C36: =SUM(C30,C34) -> 82035 | D36: =SUM(D30,D34) -> 101092.17 | E36: =SUM(E30,E34) -> 117415.62 | F36: =SUM(F30,F34) -> 137429.62 | G36: =SUM(G30,G34) -> 158128.95 | H36: =SUM(H30,H34) -> 176755.62
B38: Balance Sheet Check | C38: =C23-C36 -> 0 | D38: =D23-D36 -> 0 | E38: =E23-E36 -> 0 | F38: =F23-F36 -> 0 | G38: =G23-G36 -> 0 | H38: =H23-H36 -> 0
A40: X | B40: Cash Flow Statement
B41: Net Income | D41: =D14 -> 27211.234 | E41: =E14 -> 27987.156 | F41: =F14 -> 35072.346 | G41: =G14 -> 40650.704 | H41: =H14 -> 42702.857
B42: Depreciation | D42: =D100 -> 6399 | E42: =E100 -> 7599 | F42: =F100 -> 8599 | G42: =G100 -> 9349 | H42: =H100 -> 10099
B43: Change in Accounts Receivable | D43: =-D19+C19 -> -2446.4983 | E43: =-E19+D19 -> -616.17492 | F43: =-F19+E19 -> -924.26237 | G43: =-G19+F19 -> -770.21864 | H43: =-H19+G19 -> -770.21864
B44: Change in Inventory | D44: =-D20+C20 -> -1064.2667 | E44: =-E20+D20 -> -482.16334 | F44: =-F20+E20 -> 33.639303 | G44: =-G20+F20 -> -28.032752 | H44: =-H20+G20 -> -532.62229
B45: Change in Accounts Payable | D45: =D25-C25 -> 1845.9365 | E45: =E25-D25 -> 836.29682 | F45: =F25-E25 -> -58.34629 | G45: =G25-F25 -> 48.621908 | H45: =H25-G25 -> 923.81626
B46: Cash Flow from Operating Activities | D46: =SUM(D41:D45) -> 31945.405 | E46: =SUM(E41:E45) -> 35324.115 | F46: =SUM(F41:F45) -> 42722.377 | G46: =SUM(G41:G45) -> 49250.075 | H46: =SUM(H41:H45) -> 52422.833
B48: Capital Expenditures | D48: =-D85 -> -15000 | E48: =-E85 -> -12000 | F48: =-F85 -> -10000 | G48: =-G85 -> -7500 | H48: =-H85 -> -7500
B49: Cash Flow from Investing Activities | D49: =D48 -> -15000 | E49: =E48 -> -12000 | F49: =F48 -> -10000 | G49: =G48 -> -7500 | H49: =H48 -> -7500
B51: Change in LT Debt | D51: =D79-E79 -> 0 | E51: =E79-F79 -> 0 | F51: =F79-G79 -> 0 | G51: =G79-H79 -> 0 | H51: =0 -> 0
B52: Change in Revolver
B53: Change in Common Stock | D53: =D32-C32 -> 0 | E53: =E32-D32 -> 0 | F53: =F32-E32 -> 0 | G53: =G32-F32 -> 0 | H53: =H32-G32 -> 0
B54: Dividends | D54: =D110 -> -10000 | E54: =E110 -> -12500 | F54: =F110 -> -15000 | G54: =G110 -> -20000 | H54: =H110 -> -25000
B55: Cash Flow from Financing Activities | D55: =SUM(D51:D54) -> -10000 | E55: =SUM(E51:E54) -> -12500 | F55: =SUM(F51:F54) -> -15000 | G55: =SUM(G51:G54) -> -20000 | H55: =SUM(H51:H54) -> -25000
B57: Beginning of Year Cash Balance | D57: =C18 -> 14589 | E57: =D59 -> 21534.405 | F57: =E59 -> 32358.52 | G57: =F59 -> 50080.897 | H57: =G59 -> 71830.972
B58: Change in Cash | D58: =D46+D49+D55 -> 6945.4054 | E58: =E46+E49+E55 -> 10824.115 | F58: =F46+F49+F55 -> 17722.377 | G58: =G46+G49+G55 -> 21750.075 | H58: =H46+H49+H55 -> 19922.833
B59: End of Year Cash Balance | D59: =D57+D58 -> 21534.405 | E59: =E57+E58 -> 32358.52 | F59: =F57+F58 -> 50080.897 | G59: =G57+G58 -> 71830.972 | H59: =H57+H58 -> 91753.805
A61: X | B61: Assumptions
B62: Income Statement Assumptions | C62: 2025 | D62: 2026 | E62: 2027 | F62: 2028 | G62: 2029 | H62: 2030
B63: Units Sold | D63: 400 | E63: 420 | F63: 450 | G63: 475 | H63: 500
B64: Price per Unit | D64: 495.95 | E64: 495.95 | F64: 495.95 | G64: 495.95 | H64: 495.95
B66: COGS as a % of Rev | D66: 0.43 | E66: 0.43 | F66: 0.4 | G66: 0.38 | H66: 0.38
B67: SG&A as a % of Rev | D67: 0.35 | E67: 0.35 | F67: 0.35 | G67: 0.35 | H67: 0.35
B69: Tax Rate | D69: 0.21 | E69: 0.21 | F69: 0.21 | G69: 0.21 | H69: 0.21
B71: Revenue | C71: 158997
B72: COGS | C72: 75889
B74: Balance Sheet Assumptions
B75: =B19&" as a % of Rev" -> Accounts Receivable as a % of Rev | D75: =C19/C71 -> 0.062120669 | E75: =C19/C71 -> 0.062120669 | F75: =C19/C71 -> 0.062120669 | G75: =C19/C71 -> 0.062120669 | H75: =C19/C71 -> 0.062120669 | J75: AR=x% of revenue
B76: =B20&" as a % of COGS" -> Inventory as a % of COGS | D76: =C20/C72 -> 0.11304669 | E76: =C20/C72 -> 0.11304669 | F76: =C20/C72 -> 0.11304669 | G76: =C20/C72 -> 0.11304669 | H76: =C20/C72 -> 0.11304669 | J76: Inventory = x% of COGS
B77: =B25&" as a % of COGS" -> Accounts Payable as a % of COGS | D77: =C25/C72 -> 0.19607585 | E77: =C25/C72 -> 0.19607585 | F77: =C25/C72 -> 0.19607585 | G77: =C25/C72 -> 0.19607585 | H77: =C25/C72 -> 0.19607585 | J77: AP = x% of COGS
B79: Long Term Debt | D79: 40000 | E79: =D79 -> 40000 | F79: =E79 -> 40000 | G79: =F79 -> 40000 | H79: =G79 -> 40000
B80: Interest Expense % | D80: 0.07 | E80: 0.07 | F80: 0.07 | G80: 0.07 | H80: 0.07
B81: Interest Expense | D81: =D79*D80 -> 2800 | E81: =E79*E80 -> 2800 | F81: =F79*F80 -> 2800 | G81: =G79*G80 -> 2800 | H81: =H79*H80 -> 2800
A83: X | B83: Supporting Schedules
B84: Fixed Assets Schedule
B85: Capex | D85: 15000 | E85: 12000 | F85: 10000 | G85: 7500 | H85: 7500
B87: Existing Assets Useful Life (years) | C87: 10
B88: New Assets Useful Life (years) | C88: 10
B89: PP&E 2025 EOP | C89: =C22 -> 48990 | D89: =C89-D100 -> 42591 | E89: =D89-E100 -> 34992 | F89: =E89-F100 -> 26393 | G89: =F89-G100 -> 17044 | H89: =G89-H100 -> 6945
C91: Capex | D91: 2026 | E91: 2027 | F91: 2028 | G91: 2029 | H91: 2030 | J91: Dep Methods
C92: {=TRANSPOSE(D85:H85)} -> 15000 | D92: =$C92/$C$88 -> 1500 | E92: =$C92/$C$88 -> 1500 | F92: =$C92/$C$88 -> 1500 | G92: =$C92/$C$88 -> 1500 | H92: =$C92/$C$88 -> 1500 | J92: 1. SLM = VALUE OF ASSET - SCRAP VALUE / USEFUL LIFE OF ASSET
C93: 12000 | E93: =$C93/$C$88 -> 1200 | F93: =$C93/$C$88 -> 1200 | G93: =$C93/$C$88 -> 1200 | H93: =$C93/$C$88 -> 1200 | J93: 2. WDV = VALUE OF ASSET x % OF DEP
C94: 10000 | F94: =$C94/$C$88 -> 1000 | G94: =$C94/$C$88 -> 1000 | H94: =$C94/$C$88 -> 1000
C95: 7500 | G95: =$C95/$C$88 -> 750 | H95: =$C95/$C$88 -> 750
C96: 7500 | H96: =$C96/$C$88 -> 750
B98: Existing Asset Depreciation | D98: =C89/C88 -> 4899 | E98: =D98 -> 4899 | F98: =E98 -> 4899 | G98: =F98 -> 4899 | H98: =G98 -> 4899
B99: New Assets Depreciation | D99: =SUM(D92:D96) -> 1500 | E99: =SUM(E92:E96) -> 2700 | F99: =SUM(F92:F96) -> 3700 | G99: =SUM(G92:G96) -> 4450 | H99: =SUM(H92:H96) -> 5200
B100: Total Depreciation | D100: =SUM(D98:D99) -> 6399 | E100: =SUM(E98:E99) -> 7599 | F100: =SUM(F98:F99) -> 8599 | G100: =SUM(G98:G99) -> 9349 | H100: =SUM(H98:H99) -> 10099
B102: Beginning PPE | D102: =C22 -> 48990 | E102: =D105 -> 57591 | F102: =E105 -> 61992 | G102: =F105 -> 63393 | H102: =G105 -> 61544 | J102: Last year's closing balance will be the opening blance for the next year
B103: Capex | D103: =D85 -> 15000 | E103: =E85 -> 12000 | F103: =F85 -> 10000 | G103: =G85 -> 7500 | H103: =H85 -> 7500
B104: Depreciation | D104: =-D100 -> -6399 | E104: =-E100 -> -7599 | F104: =-F100 -> -8599 | G104: =-G100 -> -9349 | H104: =-H100 -> -10099
B105: Ending PPE | D105: =SUM(D102:D104) -> 57591 | E105: =SUM(E102:E104) -> 61992 | F105: =SUM(F102:F104) -> 63393 | G105: =SUM(G102:G104) -> 61544 | H105: =SUM(H102:H104) -> 58945
A107: X | B107: Retained Earnings Schedule
B108: Beginning of Period RE | D108: =C33 -> 2155 | E108: =D111 -> 19366.234 | F108: =E111 -> 34853.39 | G108: =F111 -> 54925.736 | H108: =G111 -> 75576.441
B109: Net Income | D109: =D14 -> 27211.234 | E109: =E14 -> 27987.156 | F109: =F14 -> 35072.346 | G109: =G14 -> 40650.704 | H109: =H14 -> 42702.857
B110: Dividends | D110: -10000 | E110: -12500 | F110: -15000 | G110: -20000 | H110: -25000
B111: End of Period RE | D111: =SUM(D108:D110) -> 19366.234 | E111: =SUM(E108:E110) -> 34853.39 | F111: =SUM(F108:F110) -> 54925.736 | G111: =SUM(G108:G110) -> 75576.441 | H111: =SUM(H108:H110) -> 93279.298
A113: X | B113: Revolver
B114: Available Cash
B115: Beginning Cash Balance | D115: =C18 -> 14589 | E115: =D121 -> 21534.405 | F115: =E121 -> 32358.52 | G115: =F121 -> 50080.897 | H115: =G121 -> 71830.972
B116: Cash from operations | D116: =D46 -> 31945.405 | E116: =E46 -> 35324.115 | F116: =F46 -> 42722.377 | G116: =G46 -> 49250.075 | H116: =H46 -> 52422.833
B117: Cash from Investing | D117: =D49 -> -15000 | E117: =E49 -> -12000 | F117: =F49 -> -10000 | G117: =G49 -> -7500 | H117: =H49 -> -7500
B118: Change in LT Debt | D118: =0 -> 0 | E118: =0 -> 0 | F118: =0 -> 0 | G118: =0 -> 0 | H118: =0 -> 0
B119: Change in Common Stock | D119: =0 -> 0 | E119: =0 -> 0 | F119: =0 -> 0 | G119: =0 -> 0 | H119: =0 -> 0
B120: Dividends | D120: =D110 -> -10000 | E120: =E110 -> -12500 | F120: =F110 -> -15000 | G120: =G110 -> -20000 | H120: =H110 -> -25000
B121: Cash Available for Revolver | D121: =SUM(D115:D120) -> 21534.405 | E121: =SUM(E115:E120) -> 32358.52 | F121: =SUM(F115:F120) -> 50080.897 | G121: =SUM(G115:G120) -> 71830.972 | H121: =SUM(H115:H120) -> 91753.805
B123: Revolver
B124: Beginning Balance | D124: =C26 -> 0 | E124: =D126 -> 0 | F124: =E126 -> 0 | G124: =F126 -> 0 | H124: =G126 -> 0
B125: Change in Revolver | D125: =IF(D121<0,-D121,-MIN(D124,D121)) -> 0 | E125: =IF(E121<0,-E121,-MIN(E124,E121)) -> 0 | F125: =IF(F121<0,-F121,-MIN(F124,F121)) -> 0 | G125: =IF(G121<0,-G121,-MIN(G124,G121)) -> 0 | H125: =IF(H121<0,-H121,-MIN(H124,H121)) -> 0
...

Sheet Sensitivity Analysis
A1: NET INCOME SENSITIVITY ANALYSIS
A3: BASE NET INCOME | D3: =statements!H14 -> 42702.857
A5: Units Sold Sensitivity | C5: 37% | D5: 38% (Base) | E5: 39%
A6: 490 | B6: COGS % | C6: =statements!D135 -> 43564.819 | D6: =statements!E135 -> 41644.996 | E6: =statements!F135 -> 39725.174
A7: 500 (Base) | C7: =statements!D136 -> 44661.86 | D7: =statements!E136 -> 42702.857 | E7: =statements!F136 -> 40743.855
A8: 510 | C8: =statements!D137 -> 45758.901 | D8: =statements!E137 -> 43760.719 | E8: =statements!F137 -> 41762.536

Sheet Debt Schedule
A1: LONG TERM DEBT SCHEDULE
A3: Description | B3: 2025 | C3: 2026 | D3: 2027 | E3: 2028 | F3: 2029 | G3: 2030
A4: Beginning Balance | B4: =statements!C29 -> 40000 | C4: =B7 -> 40000 | D4: =C7 -> 40000 | E4: =D7 -> 40000 | F4: =E7 -> 40000 | G4: =F7 -> 40000
A5: Debt Issuance | B5: 0 | C5: 0 | D5: 0 | E5: 0 | F5: 0 | G5: 0
A6: Principal Repayment | B6: 0 | C6: 0 | D6: 0 | E6: 0 | F6: 0 | G6: 0
A7: Ending Balance | B7: =B4+B5-B6 -> 40000 | C7: =C4+C5-C6 -> 40000 | D7: =D4+D5-D6 -> 40000 | E7: =E4+E5-E6 -> 40000 | F7: =F4+F5-F6 -> 40000 | G7: =G4+G5-G6 -> 40000
A9: INTEREST EXPENSE SCHEDULE
A11: Beginning Debt Balance | B11: =B4 -> 40000 | C11: =C4 -> 40000 | D11: =D4 -> 40000 | E11: =E4 -> 40000 | F11: =F4 -> 40000 | G11: =G4 -> 40000
A12: Interest Rate | B12: =statements!D80 -> 0.07 | C12: =statements!D80 -> 0.07 | D12: =statements!D80 -> 0.07 | E12: =statements!D80 -> 0.07 | F12: =statements!D80 -> 0.07 | G12: =statements!D80 -> 0.07
A13: Interest Expense | B13: =B11*B12 -> 2800 | C13: =C11*C12 -> 2800 | D13: =D11*D12 -> 2800 | E13: =E11*E12 -> 2800 | F13: =F11*F12 -> 2800 | G13: =G11*G12 -> 2800
